odoo/addons/edi_voxel_stock_picking/README.rst
odoo/addons/edi_voxel_stock_picking/__init__.py
odoo/addons/edi_voxel_stock_picking/__manifest__.py
odoo/addons/edi_voxel_stock_picking/data/ir_cron_data.xml
odoo/addons/edi_voxel_stock_picking/i18n/edi_voxel_stock_picking.pot
odoo/addons/edi_voxel_stock_picking/i18n/es.po
odoo/addons/edi_voxel_stock_picking/models/__init__.py
odoo/addons/edi_voxel_stock_picking/models/res_company.py
odoo/addons/edi_voxel_stock_picking/models/res_config_settings.py
odoo/addons/edi_voxel_stock_picking/models/stock_picking.py
odoo/addons/edi_voxel_stock_picking/readme/CONFIGURE.rst
odoo/addons/edi_voxel_stock_picking/readme/CONTRIBUTORS.rst
odoo/addons/edi_voxel_stock_picking/readme/DESCRIPTION.rst
odoo/addons/edi_voxel_stock_picking/readme/USAGE.rst
odoo/addons/edi_voxel_stock_picking/reports/__init__.py
odoo/addons/edi_voxel_stock_picking/reports/report_voxel_picking.py
odoo/addons/edi_voxel_stock_picking/static/description/icon.png
odoo/addons/edi_voxel_stock_picking/static/description/index.html
odoo/addons/edi_voxel_stock_picking/tests/__init__.py
odoo/addons/edi_voxel_stock_picking/tests/test_voxel_stock_picking.py
odoo/addons/edi_voxel_stock_picking/views/report_voxel_picking.xml
odoo/addons/edi_voxel_stock_picking/views/res_company_view.xml
odoo/addons/edi_voxel_stock_picking/views/res_config_settings_views.xml
odoo/addons/edi_voxel_stock_picking/views/stock_picking_views.xml
odoo13_addon_edi_voxel_stock_picking-13.0.1.0.4.dist-info/METADATA
odoo13_addon_edi_voxel_stock_picking-13.0.1.0.4.dist-info/WHEEL
odoo13_addon_edi_voxel_stock_picking-13.0.1.0.4.dist-info/top_level.txt
odoo13_addon_edi_voxel_stock_picking-13.0.1.0.4.dist-info/RECORD
