Metadata-Version: 2.1
Name: odoo13-addon-edi-voxel-stock-picking
Version: 13.0.1.0.4
Summary: Sends stock picking report to Voxel.
Home-page: https://github.com/OCA/edi
Author: Tecnativa, Odoo Community Association (OCA)
Author-email: support@odoo-community.org
License: AGPL-3
Platform: UNKNOWN
Classifier: Programming Language :: Python
Classifier: Framework :: Odoo
Classifier: Framework :: Odoo :: 13.0
Classifier: License :: OSI Approved :: GNU Affero General Public License v3
Requires-Python: >=3.5
Requires-Dist: odoo13-addon-edi-voxel
Requires-Dist: odoo (<13.1dev,>=13.0a)
